mush/__init__.py
mush/callpoints.py
mush/compat.py
mush/context.py
mush/declarations.py
mush/factory.py
mush/markers.py
mush/modifier.py
mush/plug.py
mush/runner.py
mush/tests/__init__.py
mush/tests/configparser.py
mush/tests/conftest.py
mush/tests/example_with_mush_clone.py
mush/tests/example_with_mush_factory.py
mush/tests/example_without_mush.py
mush/tests/test_callpoints.py
mush/tests/test_context.py
mush/tests/test_declarations.py
mush/tests/test_declarations_py3.py
mush/tests/test_example_with_mush_clone_py3.py
mush/tests/test_example_with_mush_factory_py3.py
mush/tests/test_example_without_mush.py
mush/tests/test_factory.py
mush/tests/test_marker.py
mush/tests/test_plug.py
mush/tests/test_runner.py
mush-2.8.1.dist-info/METADATA
mush-2.8.1.dist-info/WHEEL
mush-2.8.1.dist-info/top_level.txt
mush-2.8.1.dist-info/RECORD
